trivial_records.py
trivial_records-0.0.4.dist-info/licenses/LICENSE
trivial_records-0.0.4.dist-info/METADATA
trivial_records-0.0.4.dist-info/WHEEL
trivial_records-0.0.4.dist-info/top_level.txt
trivial_records-0.0.4.dist-info/RECORD
