Metadata-Version: 2.4
Name: trivial-records
Version: 0.0.4
Summary: Tiny library that parses and generates text containing lists of records.
Author-email: Leonardo Nobrega <leonobr@gmail.com>
License-Expression: Unlicense
Project-URL: Homepage, https://github.com/leonardo-nobrega/trivial-records
Project-URL: Issues, https://github.com/leonardo-nobrega/trivial-records/issues
Classifier: Programming Language :: Python :: 3
Classifier: Operating System :: OS Independent
Requires-Python: >=3.12
License-File: LICENSE
Dynamic: license-file
